LICENSE
MANIFEST.in
README.md
setup.py
clusterondemandvmware/__init__.py
clusterondemandvmware/_version.py
clusterondemandvmware/brightsetup.py
clusterondemandvmware/cli.py
clusterondemandvmware/clientutils.py
clusterondemandvmware/clusterconsole.py
clusterondemandvmware/clustercreate.py
clusterondemandvmware/clusterdelete.py
clusterondemandvmware/clusterlist.py
clusterondemandvmware/clustershow.py
clusterondemandvmware/clusterstart.py
clusterondemandvmware/clusterstop.py
clusterondemandvmware/configdump.py
clusterondemandvmware/configshow.py
clusterondemandvmware/configuration.py
clusterondemandvmware/findclusters.py
clusterondemandvmware/imagedelete.py
clusterondemandvmware/imageinstall.py
clusterondemandvmware/imagelist.py
clusterondemandvmware/imagerepolist.py
clusterondemandvmware/images.py
clusterondemandvmware/imagetag.py
clusterondemandvmware/network.py
clusterondemandvmware/nsx.py
clusterondemandvmware/ssh.py
clusterondemandvmware/summary.py
clusterondemandvmware/utils.py
clusterondemandvmware/cloudconfig/__init__.py
clusterondemandvmware/cloudconfig/cloudconfig.py
cm_cluster_on_demand_vmware.egg-info/PKG-INFO
cm_cluster_on_demand_vmware.egg-info/SOURCES.txt
cm_cluster_on_demand_vmware.egg-info/dependency_links.txt
cm_cluster_on_demand_vmware.egg-info/entry_points.txt
cm_cluster_on_demand_vmware.egg-info/requires.txt
cm_cluster_on_demand_vmware.egg-info/top_level.txt