Metadata-Version: 2.1
Name: cm-cluster-on-demand-vmware
Version: 9.2.7
Summary: Bright Cluster on Demand for VMWare
Home-page: https://www.brightcomputing.com/
Author: Cloudteam
Author-email: cloudteam@brightcomputing.com
License: UNKNOWN
Platform: UNKNOWN
Classifier: Development Status :: 5 - Production/Stable
Classifier: Intended Audience :: Information Technology
Classifier: Intended Audience :: Science/Research
Classifier: Intended Audience :: System Administrators
Classifier: License :: OSI Approved :: Apache Software License
Classifier: Programming Language :: Python :: 3 :: Only
Classifier: Programming Language :: Python :: 3.9
Classifier: Topic :: System :: Clustering
Classifier: Topic :: System :: Installation/Setup
Classifier: Topic :: System :: Monitoring
Classifier: Topic :: System :: Systems Administration
Requires-Python: >=3.9
License-File: LICENSE
